ai_commit/__init__.py
ai_commit/app.py
ai_commit/prompts.py
ai_commit/providers.py
ai_commit/utils.py
ai_gen_commit-0.1.0.dist-info/licenses/LICENSE
ai_gen_commit-0.1.0.dist-info/METADATA
ai_gen_commit-0.1.0.dist-info/WHEEL
ai_gen_commit-0.1.0.dist-info/entry_points.txt
ai_gen_commit-0.1.0.dist-info/top_level.txt
ai_gen_commit-0.1.0.dist-info/RECORD
