Metadata-Version: 2.4
Name: ai-gen-commit
Version: 0.1.0
Summary: AI generated commit messages!
Author: Yankee Maharjan
Project-URL: Repository, https://github.com/yankeexe/ai-gen-commit
Keywords: ai commit,commit ai,ai generated commit,llm commit,generative ai commit
Classifier: Programming Language :: Python :: 3.10
Classifier: Programming Language :: Python :: 3.11
Classifier: Intended Audience :: Developers
Classifier: Development Status :: 4 - Beta
Requires-Python: >=3.10
License-File: LICENSE
Requires-Dist: openai==1.93.0
Dynamic: license-file
